pipeline_sdk_test59/__init__.py
pipeline_sdk_test59/auth_service.py
pipeline_sdk_test59/inference_pipeline.py
pipeline_sdk_test59/model_inference_dsl_component.py
pipeline_sdk_test59/model_train_dsl_component.py
pipeline_sdk_test59/model_validate_dsl_component.py
pipeline_sdk_test59/pipeline_util.py
pipeline_sdk_test59/run_inference_pipeline.py
pipeline_sdk_test59/run_training_pipeline.py
pipeline_sdk_test59/run_validate_pipeline.py
pipeline_sdk_test59/train_pipeline.py
pipeline_sdk_test59/validate_pipeline.py
pipeline_sdk_test59-1.0.0.dist-info/METADATA
pipeline_sdk_test59-1.0.0.dist-info/WHEEL
pipeline_sdk_test59-1.0.0.dist-info/top_level.txt
pipeline_sdk_test59-1.0.0.dist-info/RECORD
